Workbook
Name bb_rate: Assumptions!$B$28
Name blended_var_cost: 'User Profiles'!$J$8
Name browser_calls: Assumptions!$B$39
Name cached_share: Assumptions!$B$35
Name credits_per_window: Assumptions!$B$5
Name days_per_month: Assumptions!$B$9
Name exa_rate: Assumptions!$B$29
Name fixed_launch: 'Fixed Costs'!$E$21
Name fixed_today: 'Fixed Costs'!$D$21
Name free_max_credits: Allowance!$B$10
Name free_user_cost: 'User Profiles'!$J$12
Name lk_agent: Assumptions!$B$25
Name lk_participants: Assumptions!$B$27
Name lk_webrtc: Assumptions!$B$26
Name llm_cache: Assumptions!$B$22
Name llm_in: Assumptions!$B$20
Name llm_out: Assumptions!$B$21
Name paid_credits_per_window: Assumptions!$B$6
Name paid_max_credits: Allowance!$C$10
Name paid_worst_case: Allowance!$C$22
Name paying_subs: Pricing!$B$6
Name ref_browser: Assumptions!$B$18
Name ref_cached: Assumptions!$B$13
Name ref_in: Assumptions!$B$12
Name ref_out: Assumptions!$B$14
Name ref_stt: Assumptions!$B$15
Name ref_tts: Assumptions!$B$16
Name ref_voice: Assumptions!$B$17
Name safety_mult: Assumptions!$B$10
Name stripe_fixed: Assumptions!$B$31
Name stripe_pct: Assumptions!$B$30
Name stt_rate: Assumptions!$B$23
Name tokens_in: Assumptions!$B$33
Name tokens_out: Assumptions!$B$34
Name tts_rate: Assumptions!$B$24
Name u_browser_cr: 'Unit Costs'!$B$25
Name u_browser_usd: 'Unit Costs'!$C$25
Name u_search_cr: 'Unit Costs'!$B$26
Name u_search_usd: 'Unit Costs'!$C$26
Name u_text_cr: 'Unit Costs'!$B$23
Name u_text_usd: 'Unit Costs'!$C$23
Name u_voice_cr: 'Unit Costs'!$B$24
Name u_voice_usd: 'Unit Costs'!$C$24
Name usd_per_credit: Assumptions!$B$7
Name voice_chars: Assumptions!$B$37
Name voice_stt_min: Assumptions!$B$36
Name voice_turns: Assumptions!$B$38
Name window_hours: Assumptions!$B$8

Sheet Start Here
A1: Open Learn - expenses, allowance & pricing
A2: Built 2026-10-12 from the repo's usage policy (backend/app/usage/pricing.py, docs/UNIFIED_USAGE_ALLOWANCE_IMPLEMENTATION.md) and public provider rates.
A4: Headline numbers (live - change any input and these update)
A5: Recommended monthly price | B5: =Pricing!B18 -> 10.99
A6: Break-even price | B6: =Pricing!B16 -> 2.8241359
A7: Fully loaded cost per paying user / month | B7: =Pricing!B14 -> 2.442236
A8: Gross margin at recommended price | B8: =Pricing!B22 -> 0.72147898
A9: Worst-case usage cost per paying user / month | B9: =paid_worst_case -> 11.52
A10: Fixed costs per month (at paid launch) | B10: =fixed_launch -> 134.5
A11: Allowance per user | B11: =TEXT(credits_per_window,"0")&" credits every "&TEXT(window_hours,"0")&" hours (worth $"&TEXT(credits_per_window*usd_per_credit,"0.00")&")" -> 100 credits every 5 hours (worth $0.10)
A13: How to use
A14: 1. Expense Log - add every charge as it happens (date, vendor, category, amount). Monthly Summary totals it automatically.
A15: 2. Monthly Summary - each month, type in active users, paying users and revenue to see real cost per user and profit.
A16: 3. Fixed Costs - keep subscriptions current. 'At paid launch' feeds the price.
A17: 4. Assumptions - provider rates and allowance policy. Yellow cells came from third-party trackers or are product decisions: verify them.
A18: 5. User Profiles - replace the guessed usage numbers with real analytics once you have them.
A19: 6. Pricing - set paying-subscriber scale and target margin; read the recommended price and the sensitivity table.
A21: Colour key
A22: Blue text | B22: Input you can change
A23: Black text | B23: Formula - don't overwrite
A24: Green text | B24: Pulled from another tab
A25: Yellow fill | B25: Verify this / product decision
A26: Green fill | B26: Key result
A28: Sources for provider rates (checked 2026-10-12)
A29: Claude Haiku 5.5 via OpenRouter: repo doc docs/UNIFIED_USAGE_ALLOWANCE_IMPLEMENTATION.md §0 (verify https://openrouter.ai)
A30: Deepgram Flux: https://deepgram.com/pricing (third-party trackers: pricingsaas.com, usagepricing.com)
A31: ElevenLabs Flash v2.5: https://elevenlabs.io/pricing/api (via techjacksolutions.com, llmreference.com)
A32: LiveKit: https://livekit.com/pricing
A33: Exa: https://exa.ai/docs/reference/pricing
A34: Browserbase: https://www.browserbase.com/pricing (repo doc §11)
A35: Render / Supabase / Vercel: render.com/pricing, supabase.com/pricing, vercel.com/pricing (third-party summaries)

Sheet Pricing
A1: What to charge
A2: Price = (cost per paying user + fixed card fee) / (1 - card % - target margin). Margin = what's left after card fees and all costs.
A4: Item | B4: Value | C4: Note
A5: Inputs
A6: Paying subscribers (planning scale) | B6: 200 | C6: Fixed costs are spread over this many payers - the biggest lever at small scale
A7: Free users per paying user | B7: 4 | C7: 4 = 20% of all users pay
A8: Target gross margin | B8: 0.7 | C8: Typical SaaS target 70-80%; AI products often run 50-65%
A9: Annual plan: months charged per year | B9: 10 | C9: 10 = 'two months free' on annual billing
A10: Cost per paying user per month
A11: Variable usage cost (blended) | B11: =blended_var_cost -> 1.629736 | C11: User Profiles
A12: Free-user subsidy | B12: =B7*free_user_cost -> 0.14 | C12: Free users' AI cost, carried by payers
A13: Fixed costs share | B13: =IF(B6=0,0,fixed_launch/B6) -> 0.6725 | C13: Fixed Costs (at paid launch) / paying subscribers
A14: Fully loaded cost per paying user | B14: =SUM(B11:B13) -> 2.442236
A15: Price
A16: Break-even price | B16: =(B14+stripe_fixed)/(1-stripe_pct) -> 2.8241359 | C16: Zero profit after card fees
A17: Price for target margin | B17: =(B14+stripe_fixed)/(1-stripe_pct-B8) -> 10.118952
A18: RECOMMENDED MONTHLY PRICE | B18: =CEILING(B17,1)-0.01 -> 10.99 | C18: Target-margin price rounded up to the next .99
A19: Annual plan price | B19: =B18*B9 -> 109.9
A20: Checks at the recommended price
A21: Net revenue per user after card fees | B21: =B18*(1-stripe_pct)-stripe_fixed -> 10.37129
A22: Gross margin per average paying user | B22: =IF(B18=0,0,(B21-B14)/B18) -> 0.72147898
A23: Profit per average paying user / month | B23: =B21-B14 -> 7.929054
A24: Profit on a worst-case user (maxes every window) | B24: =B21-paid_worst_case-B12-B13 -> -1.96121 | C24: Negative = an extreme user costs more than they pay. Fix by lowering paid credits/window or capping voice
A25: Monthly profit at planning scale | B25: =B23*B6 -> 1585.8108
A27: Sensitivity: recommended price (rounded to .99) by scale and margin
A28: Paying subscribers | B28: 50% margin | C28: 60% margin | D28: 70% margin | E28: 80% margin
A29: Margin -> | B29: 0.5 | C29: 0.6 | D29: 0.7 | E29: 0.8
A30: 25 | B30: =CEILING(($B$11+$B$12+fixed_launch/$A30+stripe_fixed)/(1-stripe_pct-B$29),1)-0.01 -> 15.99 | C30: =CEILING(($B$11+$B$12+fixed_launch/$A30+stripe_fixed)/(1-stripe_pct-C$29),1)-0.01 -> 20.99 | D30: =CEILING(($B$11+$B$12+fixed_launch/$A30+stripe_fixed)/(1-stripe_pct-D$29),1)-0.01 -> 27.99 | E30: =CEILING(($B$11+$B$12+fixed_launch/$A30+stripe_fixed)/(1-stripe_pct-E$29),1)-0.01 -> 43.99
A31: 50 | B31: =CEILING(($B$11+$B$12+fixed_launch/$A31+stripe_fixed)/(1-stripe_pct-B$29),1)-0.01 -> 10.99 | C31: =CEILING(($B$11+$B$12+fixed_launch/$A31+stripe_fixed)/(1-stripe_pct-C$29),1)-0.01 -> 12.99 | D31: =CEILING(($B$11+$B$12+fixed_launch/$A31+stripe_fixed)/(1-stripe_pct-D$29),1)-0.01 -> 17.99 | E31: =CEILING(($B$11+$B$12+fixed_launch/$A31+stripe_fixed)/(1-stripe_pct-E$29),1)-0.01 -> 27.99
A32: 100 | B32: =CEILING(($B$11+$B$12+fixed_launch/$A32+stripe_fixed)/(1-stripe_pct-B$29),1)-0.01 -> 7.99 | C32: =CEILING(($B$11+$B$12+fixed_launch/$A32+stripe_fixed)/(1-stripe_pct-C$29),1)-0.01 -> 9.99 | D32: =CEILING(($B$11+$B$12+fixed_launch/$A32+stripe_fixed)/(1-stripe_pct-D$29),1)-0.01 -> 12.99 | E32: =CEILING(($B$11+$B$12+fixed_launch/$A32+stripe_fixed)/(1-stripe_pct-E$29),1)-0.01 -> 19.99
A33: 200 | B33: =CEILING(($B$11+$B$12+fixed_launch/$A33+stripe_fixed)/(1-stripe_pct-B$29),1)-0.01 -> 5.99 | C33: =CEILING(($B$11+$B$12+fixed_launch/$A33+stripe_fixed)/(1-stripe_pct-C$29),1)-0.01 -> 7.99 | D33: =CEILING(($B$11+$B$12+fixed_launch/$A33+stripe_fixed)/(1-stripe_pct-D$29),1)-0.01 -> 10.99 | E33: =CEILING(($B$11+$B$12+fixed_launch/$A33+stripe_fixed)/(1-stripe_pct-E$29),1)-0.01 -> 16.99
A34: 500 | B34: =CEILING(($B$11+$B$12+fixed_launch/$A34+stripe_fixed)/(1-stripe_pct-B$29),1)-0.01 -> 4.99 | C34: =CEILING(($B$11+$B$12+fixed_launch/$A34+stripe_fixed)/(1-stripe_pct-C$29),1)-0.01 -> 6.99 | D34: =CEILING(($B$11+$B$12+fixed_launch/$A34+stripe_fixed)/(1-stripe_pct-D$29),1)-0.01 -> 8.99 | E34: =CEILING(($B$11+$B$12+fixed_launch/$A34+stripe_fixed)/(1-stripe_pct-E$29),1)-0.01 -> 13.99
A35: 1000 | B35: =CEILING(($B$11+$B$12+fixed_launch/$A35+stripe_fixed)/(1-stripe_pct-B$29),1)-0.01 -> 4.99 | C35: =CEILING(($B$11+$B$12+fixed_launch/$A35+stripe_fixed)/(1-stripe_pct-C$29),1)-0.01 -> 5.99 | D35: =CEILING(($B$11+$B$12+fixed_launch/$A35+stripe_fixed)/(1-stripe_pct-D$29),1)-0.01 -> 8.99 | E35: =CEILING(($B$11+$B$12+fixed_launch/$A35+stripe_fixed)/(1-stripe_pct-E$29),1)-0.01 -> 12.99
A36: 5000 | B36: =CEILING(($B$11+$B$12+fixed_launch/$A36+stripe_fixed)/(1-stripe_pct-B$29),1)-0.01 -> 4.99 | C36: =CEILING(($B$11+$B$12+fixed_launch/$A36+stripe_fixed)/(1-stripe_pct-C$29),1)-0.01 -> 5.99 | D36: =CEILING(($B$11+$B$12+fixed_launch/$A36+stripe_fixed)/(1-stripe_pct-D$29),1)-0.01 -> 7.99 | E36: =CEILING(($B$11+$B$12+fixed_launch/$A36+stripe_fixed)/(1-stripe_pct-E$29),1)-0.01 -> 12.99

Sheet Assumptions
A1: Assumptions & provider rates
A2: Blue = input you can change. Yellow = verify before relying on it (rate pulled from a third-party tracker or a product decision).
A3: Parameter | B3: Value | C3: Unit | D3: Source / note
A4: Allowance policy (what each user gets)
A5: Free credits per window | B5: 100 | C5: credits | D5: Repo: OPENLEARN_FREE_CREDITS_MICRO=100000000 (docs/UNIFIED_USAGE_ALLOWANCE_IMPLEMENTATION.md §1)
A6: Paid-plan credits per window | B6: 100 | C6: credits | D6: PRODUCT DECISION. Defaults to the current free policy; raise (e.g. 200 or 300) to give paying users more. Drives worst-case cost on the Allowance tab.
A7: Value of one credit | B7: 0.001 | C7: $ / credit | D7: Repo policy: 1 credit = $0.001 of normalized cost
A8: Window length | B8: 5 | C8: hours | D8: Repo: OPENLEARN_USAGE_WINDOW_SECONDS=18000
A9: Days per month | B9: 30 | C9: days | D9: Planning convention used in the spec
A10: Safety multiplier on provider cost | B10: 1.25 | C10: x | D10: backend/app/usage/pricing.py:25 - charge = max(reference, provider cost x 1.25)
A11: Reference rates (Open Learn policy, in credits)
A12: Uncached model input | B12: 0.5 | C12: credits / 1K tokens | D12: pricing.py: 500 microcredits per token
A13: Cached model input | B13: 0.1 | C13: credits / 1K tokens | D13: pricing.py: 100 microcredits per token
A14: Model output | B14: 2 | C14: credits / 1K tokens | D14: pricing.py: 2000 microcredits per token
A15: Speech-to-text | B15: 10 | C15: credits / audio min | D15: pricing.py
A16: Text-to-speech | B16: 60 | C16: credits / 1K chars | D16: pricing.py
A17: Voice transport/runtime | B17: 15 | C17: credits / connected min | D17: pricing.py
A18: Cloud browser | B18: 5 | C18: credits / browser min | D18: pricing.py
A19: Provider rates (what you actually pay)
A20: Claude Haiku 5.5 input | B20: 0.1 | C20: $ / 1M tokens | D20: Repo doc §0 quoting OpenRouter listing; verify live listing
A21: Claude Haiku 5.5 output | B21: 0.5 | C21: $ / 1M tokens | D21: Repo doc §0 quoting OpenRouter listing; verify live listing
A22: Claude Haiku 5.5 cache read | B22: 0.01 | C22: $ / 1M tokens | D22: Repo doc §0 quoting OpenRouter listing; verify live listing
A23: Deepgram Flux STT (streaming, English) | B23: 0.0065 | C23: $ / audio min | D23: Third-party trackers, Jun 2026 promo rate (regular $0.0077). Verify deepgram.com/pricing
A24: ElevenLabs Flash v2.5 TTS | B24: 0.05 | C24: $ / 1K chars | D24: Third-party summaries of ElevenLabs API pricing, Jul-Aug 2026. Model per repo: ELEVENLABS_MODEL=eleven_flash_v2_5. Verify elevenlabs.io/pricing/api
A25: LiveKit agent session | B25: 0.01 | C25: $ / agent min | D25: livekit.com/pricing. Set to 0 if the agent runs on your own Render worker rather than LiveKit Cloud
A26: LiveKit WebRTC participant | B26: 0.0005 | C26: $ / participant min | D26: Ship-tier overage per third-party summaries; Build tier includes 5,000 min free
A27: Participants per voice room | B27: 2 | C27: participants | D27: Learner + agent
A28: Browserbase browser time | B28: 0.002 | C28: $ / browser min | D28: Repo doc §11: Developer plan $0.12/hour after 100 included hours
A29: Exa web search | B29: 0.007 | C29: $ / search | D29: exa.ai/docs pricing: $7 / 1K requests (contents for 10 results included)
A30: Card processing - percent | B30: 0.029 | C30: % of price | D30: Typical Stripe US card rate; adjust to your processor
A31: Card processing - fixed | B31: 0.3 | C31: $ / charge | D31: Typical Stripe US card rate
A32: Activity shape (how a unit of usage looks)
A33: Input tokens per text turn | B33: 4000 | C33: tokens | D33: Spec worked example. Grows with chat history - raise if long conversations are common
A34: Output tokens per text turn | B34: 800 | C34: tokens | D34: Spec worked example
A35: Share of input served from cache | B35: 0 | C35: % | D35: Conservative 0%. Only provider-confirmed cache hits count
A36: Audio minutes sent to STT per connected minute | B36: 1 | C36: min | D36: Spec example; silence is still billed
A37: TTS characters per connected minute | B37: 450 | C37: chars | D37: Spec worked example
A38: LLM turns per connected voice minute | B38: 1 | C38: turns | D38: Spec worked example
A39: LLM calls per browser minute | B39: 1.67 | C39: calls | D39: Spec example: 5 model calls in a 3-minute browser task

Sheet Unit Costs
A1: Cost of one unit of usage
A2: Credits charged follow pricing.py: each component is billed at max(reference credits, provider $ x safety multiplier / $ per credit).
A4: Activity | B4: Component | C4: Quantity | D4: Reference credits | E4: Actual provider $ | F4: Credits charged | G4: Normalized $ (credits x $/credit)
A5: Text turn | B5: LLM call (input + cached input + output) | C5: 1 | D5: =C5*(tokens_in*(1-cached_share)*ref_in+tokens_in*cached_share*ref_cached+tokens_out*ref_out)/1000 -> 3.6 | E5: =C5*(tokens_in*(1-cached_share)*llm_in+tokens_in*cached_share*llm_cache+tokens_out*llm_out)/1000000 -> 0.0008 | F5: =MAX(D5,E5*safety_mult/usd_per_credit) -> 3.6 | G5: =F5*usd_per_credit -> 0.0036
A6: Text turn - total | D6: =SUM(D5:D5) -> 3.6 | E6: =SUM(E5:E5) -> 0.0008 | F6: =SUM(F5:F5) -> 3.6 | G6: =SUM(G5:G5) -> 0.0036
A8: Voice minute | B8: Speech-to-text (Deepgram) | C8: =voice_stt_min -> 1 | D8: =C8*ref_stt -> 10 | E8: =C8*stt_rate -> 0.0065 | F8: =MAX(D8,E8*safety_mult/usd_per_credit) -> 10 | G8: =F8*usd_per_credit -> 0.01
A9: Voice minute | B9: Text-to-speech chars (ElevenLabs) | C9: =voice_chars -> 450 | D9: =C9/1000*ref_tts -> 27 | E9: =C9/1000*tts_rate -> 0.0225 | F9: =MAX(D9,E9*safety_mult/usd_per_credit) -> 28.125 | G9: =F9*usd_per_credit -> 0.028125
A10: Voice minute | B10: Realtime room + agent (LiveKit) | C10: 1 | D10: =C10*ref_voice -> 15 | E10: =C10*(lk_agent+lk_webrtc*lk_participants) -> 0.011 | F10: =MAX(D10,E10*safety_mult/usd_per_credit) -> 15 | G10: =F10*usd_per_credit -> 0.015
A11: Voice minute | B11: LLM turns | C11: =voice_turns -> 1 | D11: =C11*$D$6 -> 3.6 | E11: =C11*$E$6 -> 0.0008 | F11: =C11*$F$6 -> 3.6 | G11: =F11*usd_per_credit -> 0.0036
A12: Voice minute - total | D12: =SUM(D8:D11) -> 55.6 | E12: =SUM(E8:E11) -> 0.0408 | F12: =SUM(F8:F11) -> 56.725 | G12: =SUM(G8:G11) -> 0.056725
A14: Browser minute | B14: Cloud browser time (Browserbase) | C14: 1 | D14: =C14*ref_browser -> 5 | E14: =C14*bb_rate -> 0.002 | F14: =MAX(D14,E14*safety_mult/usd_per_credit) -> 5 | G14: =F14*usd_per_credit -> 0.005
A15: Browser minute | B15: LLM actions | C15: =browser_calls -> 1.67 | D15: =C15*$D$6 -> 6.012 | E15: =C15*$E$6 -> 0.001336 | F15: =C15*$F$6 -> 6.012 | G15: =F15*usd_per_credit -> 0.006012
A16: Browser minute - total | D16: =SUM(D14:D15) -> 11.012 | E16: =SUM(E14:E15) -> 0.003336 | F16: =SUM(F14:F15) -> 11.012 | G16: =SUM(G14:G15) -> 0.011012
A18: Web search | B18: Exa search (contents for 10 results included) | C18: 1 | D18: 0 | E18: =C18*exa_rate -> 0.007 | F18: =MAX(D18,E18*safety_mult/usd_per_credit) -> 8.75 | G18: =F18*usd_per_credit -> 0.00875
A19: Web search - total | D19: =SUM(D18:D18) -> 0 | E19: =SUM(E18:E18) -> 0.007 | F19: =SUM(F18:F18) -> 8.75 | G19: =SUM(G18:G18) -> 0.00875
A21: Summary per unit
A22: Activity | B22: Credits per unit | C22: Actual provider $ per unit | D22: Normalized $ per unit | E22: Units per FREE window | F22: Actual $ for one fully used free window | G22: Actual cost as % of credit value
A23: Text turn | B23: =F6 -> 3.6 | C23: =E6 -> 0.0008 | D23: =G6 -> 0.0036 | E23: =IF(B23=0,0,credits_per_window/B23) -> 27.777778 | F23: =E23*C23 -> 0.022222222 | G23: =IF(D23=0,0,C23/D23) -> 0.22222222
A24: Voice minute | B24: =F12 -> 56.725 | C24: =E12 -> 0.0408 | D24: =G12 -> 0.056725 | E24: =IF(B24=0,0,credits_per_window/B24) -> 1.7628911 | F24: =E24*C24 -> 0.071925959 | G24: =IF(D24=0,0,C24/D24) -> 0.71925959
A25: Browser minute | B25: =F16 -> 11.012 | C25: =E16 -> 0.003336 | D25: =G16 -> 0.011012 | E25: =IF(B25=0,0,credits_per_window/B25) -> 9.0810025 | F25: =E25*C25 -> 0.030294224 | G25: =IF(D25=0,0,C25/D25) -> 0.30294224
A26: Web search | B26: =F19 -> 8.75 | C26: =E19 -> 0.007 | D26: =G19 -> 0.00875 | E26: =IF(B26=0,0,credits_per_window/B26) -> 11.428571 | F26: =E26*C26 -> 0.08 | G26: =IF(D26=0,0,C26/D26) -> 0.8
A28: Reading it: 'Actual cost as % of credit value' below 100% means the reference rate is the binding charge, so real spend is lower than the credits imply.

Sheet Allowance
A1: Allowance given to each user
A2: Every user gets a fresh allowance each window. The window starts on first paid use and lasts 5 hours; unused credit does not roll over.
A4: Metric | B4: Free plan | C4: Paid plan | D4: Note
A5: Policy
A6: Credits per window | B6: =credits_per_window -> 100 | C6: =paid_credits_per_window -> 100 | D6: From Assumptions
A7: Credit value per window ($, normalized) | B7: =B6*usd_per_credit -> 0.1 | C7: =C6*usd_per_credit -> 0.1 | D7: What the credits are worth at reference rates - not your bill
A8: Max windows per day | B8: =24/window_hours -> 4.8 | C8: =24/window_hours -> 4.8 | D8: Only if the user starts a new window the moment the last one expires, around the clock
A9: Max windows per month | B9: =days_per_month*24/window_hours -> 144 | C9: =days_per_month*24/window_hours -> 144 | D9: 144 with 5-hour windows and 30 days
A10: Max credits per month | B10: =B6*B9 -> 14400 | C10: =C6*C9 -> 14400
A11: Max credit value per month ($, normalized) | B11: =B10*usd_per_credit -> 14.4 | C11: =C10*usd_per_credit -> 14.4 | D11: Spec: $14.40 per 30 days at 100 credits
A12: What one full window buys (if spent on one thing)
A13: Text turns | B13: =B6/u_text_cr -> 27.777778 | C13: =C6/u_text_cr -> 27.777778 | D13: Turn size set on Assumptions
A14: Voice minutes | B14: =B6/u_voice_cr -> 1.7628911 | C14: =C6/u_voice_cr -> 1.7628911 | D14: Voice is the expensive activity
A15: Cloud browser minutes | B15: =B6/u_browser_cr -> 9.0810025 | C15: =C6/u_browser_cr -> 9.0810025 | D15: Includes LLM actions
A16: Web searches | B16: =B6/u_search_cr -> 11.428571 | C16: =C6/u_search_cr -> 11.428571
A17: Worst case: actual provider cost if a user maxes EVERY window for a month
A18: All text (Claude Haiku 5.5) | B18: =B10/u_text_cr*u_text_usd -> 3.2 | C18: =C10/u_text_cr*u_text_usd -> 3.2 | D18: Free plan currently routes to openrouter/free, so its real text cost is $0 until paid routes are enabled for free users
A19: All voice | B19: =B10/u_voice_cr*u_voice_usd -> 10.357338 | C19: =C10/u_voice_cr*u_voice_usd -> 10.357338 | D19: Voice is gated to paid routes in the repo
A20: All cloud browser | B20: =B10/u_browser_cr*u_browser_usd -> 4.3623683 | C20: =C10/u_browser_cr*u_browser_usd -> 4.3623683
A21: All web search | B21: =B10/u_search_cr*u_search_usd -> 11.52 | C21: =C10/u_search_cr*u_search_usd -> 11.52
A22: Worst-case cost per user per month | B22: =MAX(B18:B21) -> 11.52 | C22: =MAX(C18:C21) -> 11.52 | D22: Theoretical ceiling. Real users sleep - see User Profiles for realistic cost
A24: Platform exposure (all users together)
A25: Free accounts | B25: 500 | D25: Input: how many free accounts you expect
A26: Paying accounts | B26: =paying_subs -> 200 | D26: Linked from Pricing
A27: Platform monthly budget cap ($) | B27: 100 | D27: Repo default: OPENLEARN_PLATFORM_MONTHLY_BUDGET_USD=100. Paid work is refused once hit
A28: Expected paid-user variable spend / month | B28: =B26*blended_var_cost -> 325.9472 | D28: Paying accounts x blended cost from User Profiles
A29: Expected free-user variable spend / month | B29: =B25*free_user_cost -> 17.5 | D29: Free accounts x free-user cost from User Profiles
A30: Total expected variable spend / month | B30: =B28+B29 -> 343.4472 | D30: If this exceeds the cap, raise the cap before launch or users will see 'service capacity' errors
A31: Cap headroom (cap - expected spend) | B31: =B27-B30 -> -243.4472

Sheet User Profiles
A1: Realistic usage per user per month
A2: Edit the blue usage numbers and mix once you have real analytics (Usage settings / provider dashboards). Usage above the paid allowance is capped.
A4: Profile | B4: Share of paying users | C4: Text turns / month | D4: Voice minutes / month | E4: Browser minutes / month | F4: Web searches / month | G4: Credits used / month | H4: % of paid monthly allowance | I4: Allowance cap factor | J4: Actual variable cost / month | K4: Credit value used / month
A5: Light | B5: 0.4 | C5: 60 | D5: 0 | E5: 0 | F5: 10 | G5: =C5*u_text_cr+D5*u_voice_cr+E5*u_browser_cr+F5*u_search_cr -> 303.5 | H5: =IF(paid_max_credits=0,0,G5/paid_max_credits) -> 0.021076389 | I5: =IF(G5=0,1,MIN(1,paid_max_credits/G5)) -> 1 | J5: =I5*(C5*u_text_usd+D5*u_voice_usd+E5*u_browser_usd+F5*u_search_usd) -> 0.118 | K5: =MIN(G5,paid_max_credits)*usd_per_credit -> 0.3035
A6: Typical | B6: 0.45 | C6: 300 | D6: 20 | E6: 10 | F6: 50 | G6: =C6*u_text_cr+D6*u_voice_cr+E6*u_browser_cr+F6*u_search_cr -> 2762.12 | H6: =IF(paid_max_credits=0,0,G6/paid_max_credits) -> 0.19181389 | I6: =IF(G6=0,1,MIN(1,paid_max_credits/G6)) -> 1 | J6: =I6*(C6*u_text_usd+D6*u_voice_usd+E6*u_browser_usd+F6*u_search_usd) -> 1.43936 | K6: =MIN(G6,paid_max_credits)*usd_per_credit -> 2.76212
A7: Heavy | B7: 0.15 | C7: 1200 | D7: 90 | E7: 60 | F7: 200 | G7: =C7*u_text_cr+D7*u_voice_cr+E7*u_browser_cr+F7*u_search_cr -> 11835.97 | H7: =IF(paid_max_credits=0,0,G7/paid_max_credits) -> 0.82194236 | I7: =IF(G7=0,1,MIN(1,paid_max_credits/G7)) -> 1 | J7: =I7*(C7*u_text_usd+D7*u_voice_usd+E7*u_browser_usd+F7*u_search_usd) -> 6.23216 | K7: =MIN(G7,paid_max_credits)*usd_per_credit -> 11.83597
A8: Blended paying user | B8: =SUM(B5:B7) -> 1 | C8: =SUMPRODUCT($B$5:$B$7,C5:C7) -> 339 | D8: =SUMPRODUCT($B$5:$B$7,D5:D7) -> 22.5 | E8: =SUMPRODUCT($B$5:$B$7,E5:E7) -> 13.5 | F8: =SUMPRODUCT($B$5:$B$7,F5:F7) -> 56.5 | G8: =SUMPRODUCT($B$5:$B$7,G5:G7) -> 3139.7495 | J8: =SUMPRODUCT($B$5:$B$7,J5:J7) -> 1.629736 | K8: =SUMPRODUCT($B$5:$B$7,K5:K7) -> 3.1397495 | L8: =IF(ABS(B8-1)>0.001,"Mix must add to 100%","")
A10: Free users (cost you carry for people who don't pay)
A11: Profile | B11: Share of free text on paid model | C11: Text turns / month | D11: Voice minutes / month | E11: Browser minutes / month | F11: Web searches / month | G11: Credits used / month | H11: % of free monthly allowance | J11: Actual variable cost / month
A12: Free user | B12: 0 | C12: 40 | D12: 0 | E12: 0 | F12: 5 | G12: =C12*u_text_cr+F12*u_search_cr -> 187.75 | H12: =IF(free_max_credits=0,0,G12/free_max_credits) -> 0.013038194 | J12: =C12*u_text_usd*B12+F12*u_search_usd -> 0.035
A13: Share on paid model = 0% matches today's config (OPENROUTER_MODEL=openrouter/free). Voice and browser are paid-only, so they stay 0 for free users.

Sheet Fixed Costs
A1: Fixed monthly costs (subscriptions & hosting)
A2: 'Today' = what you pay now. 'At paid launch' = the stack you'd need for paying users. Pricing uses the 'At paid launch' column. Annual fees are divided by 12.
A4: Item | B4: Vendor | C4: Category | D4: Today ($/mo) | E4: At paid launch ($/mo) | F4: Source / note
A5: API web service (openlearn-api) | B5: Render | C5: Hosting & Database | D5: 0 | E5: 25 | F5: deploy/render.yaml shows plan: free. Standard ~$25/mo (no spin-down) per third-party summaries of render.com/pricing
A6: Background / voice worker | B6: Render | C6: Hosting & Database | D6: 0 | E6: 25 | F6: Learning + voice agent worker. Standard ~$25/mo
A7: Key Value cache | B7: Render | C7: Hosting & Database | D7: 0 | E7: 10 | F7: render.yaml: openlearn-cache-free (plan: free). Starter ~$10/mo - verify
A8: Render workspace plan | B8: Render | C8: Hosting & Database | D8: 0 | E8: 0 | F8: Hobby $0; paid workspace tiers exist - verify render.com/pricing
A9: PostgreSQL + Auth (Supabase) | B9: Supabase | C9: Hosting & Database | D9: 0 | E9: 25 | F9: Supabase Pro $25/mo incl. $10 compute credit
A10: Web frontend | B10: Vercel | C10: Hosting & Database | D10: 0 | E10: 20 | F10: Vercel Pro $20/seat/mo for commercial use
A11: Cloud browser plan | B11: Browserbase | C11: Browser & Search | D11: 0 | E11: 20 | F11: Developer $20/mo, 100 browser hours included (repo doc §11)
A12: Realtime voice plan | B12: LiveKit | C12: Voice (STT/TTS/Realtime) | D12: 0 | E12: 0 | F12: Build tier free (1,000 agent min, 5,000 WebRTC min). Ship $50/mo when you outgrow it
A13: TTS plan | B13: ElevenLabs | C13: Voice (STT/TTS/Realtime) | D13: 0 | E13: 0 | F13: Pay-as-you-go assumed; enter subscription if you take one
A14: Domain | B14: Registrar | C14: Domains & App Stores | D14: 1.25 | E14: 1.25 | F14: ~$15/yr
A15: Apple Developer Program | B15: Apple | C15: Domains & App Stores | D15: 0 | E15: 8.25 | F15: $99/yr, needed to ship the iOS app
A16: Transactional email / monitoring | B16: Various | C16: Software & Tools | D16: 0 | E16: 0 | F16: Enter if you add e.g. Resend, Sentry
A21: Total fixed per month | D21: =SUM(D5:D20) -> 1.25 | E21: =SUM(E5:E20) -> 134.5
A22: Rows 17-20 are spare - add new subscriptions there and the total picks them up.

Sheet Expense Log
A1: Expense log - one row per charge
A2: Add a row for every invoice/charge (card statement, provider invoice, app store fee). Category and Type are drop-downs. Row 5 is an EXAMPLE - overwrite or delete it.
A4: Date | B4: Vendor | C4: Description | D4: Category | E4: Type | F4: Billing period | G4: Amount (USD) | H4: Paid via | I4: Invoice / receipt link | J4: Notes
A5: 46296 | B5: Render | C5: EXAMPLE - Starter web service, October (replace or delete) | D5: Hosting & Database | E5: Fixed | F5: Monthly | G5: 7 | H5: Visa ...1234 | I5: https://dashboard.render.com/billing

Sheet Monthly Summary
A1: Monthly summary (auto-filled from the Expense Log)
A2: Spend columns sum the log by month and category. Enter users and revenue each month (blue) to see real cost per user.
A4: Month | B4: Hosting & Database | C4: AI Models (LLM) | D4: Voice (STT/TTS/Realtime) | E4: Browser & Search | F4: Payment Fees | G4: Domains & App Stores | H4: Software & Tools | I4: Marketing | J4: Other | K4: Total spend | L4: Active users | M4: Paying users | N4: Revenue ($) | O4: Cost per active user | P4: Cost per paying user | Q4: Profit / (loss)
A5: 46296 | B5: =SUMIFS('Expense Log'!$G$5:$G$2000,'Expense Log'!$A$5:$A$2000,">="&$A5,'Expense Log'!$A$5:$A$2000,"<"&EDATE($A5,1),'Expense Log'!$D$5:$D$2000,B$4) -> 7 | C5: =SUMIFS('Expense Log'!$G$5:$G$2000,'Expense Log'!$A$5:$A$2000,">="&$A5,'Expense Log'!$A$5:$A$2000,"<"&EDATE($A5,1),'Expense Log'!$D$5:$D$2000,C$4) -> 0 | D5: =SUMIFS('Expense Log'!$G$5:$G$2000,'Expense Log'!$A$5:$A$2000,">="&$A5,'Expense Log'!$A$5:$A$2000,"<"&EDATE($A5,1),'Expense Log'!$D$5:$D$2000,D$4) -> 0 | E5: =SUMIFS('Expense Log'!$G$5:$G$2000,'Expense Log'!$A$5:$A$2000,">="&$A5,'Expense Log'!$A$5:$A$2000,"<"&EDATE($A5,1),'Expense Log'!$D$5:$D$2000,E$4) -> 0 | F5: =SUMIFS('Expense Log'!$G$5:$G$2000,'Expense Log'!$A$5:$A$2000,">="&$A5,'Expense Log'!$A$5:$A$2000,"<"&EDATE($A5,1),'Expense Log'!$D$5:$D$2000,F$4) -> 0 | G5: =SUMIFS('Expense Log'!$G$5:$G$2000,'Expense Log'!$A$5:$A$2000,">="&$A5,'Expense Log'!$A$5:$A$2000,"<"&EDATE($A5,1),'Expense Log'!$D$5:$D$2000,G$4) -> 0 | H5: =SUMIFS('Expense Log'!$G$5:$G$2000,'Expense Log'!$A$5:$A$2000,">="&$A5,'Expense Log'!$A$5:$A$2000,"<"&EDATE($A5,1),'Expense Log'!$D$5:$D$2000,H$4) -> 0 | I5: =SUMIFS('Expense Log'!$G$5:$G$2000,'Expense Log'!$A$5:$A$2000,">="&$A5,'Expense Log'!$A$5:$A$2000,"<"&EDATE($A5,1),'Expense Log'!$D$5:$D$2000,I$4) -> 0 | J5: =SUMIFS('Expense Log'!$G$5:$G$2000,'Expense Log'!$A$5:$A$2000,">="&$A5,'Expense Log'!$A$5:$A$2000,"<"&EDATE($A5,1),'Expense Log'!$D$5:$D$2000,J$4) -> 0 | K5: =SUM(B5:J5) -> 7 | O5: =IF(N(L5)=0,0,K5/L5) -> 0 | P5: =IF(N(M5)=0,0,K5/M5) -> 0 | Q5: =N(N5)-K5 -> -7
A6: 46327 | B6: =SUMIFS('Expense Log'!$G$5:$G$2000,'Expense Log'!$A$5:$A$2000,">="&$A6,'Expense Log'!$A$5:$A$2000,"<"&EDATE($A6,1),'Expense Log'!$D$5:$D$2000,B$4) -> 0 | C6: =SUMIFS('Expense Log'!$G$5:$G$2000,'Expense Log'!$A$5:$A$2000,">="&$A6,'Expense Log'!$A$5:$A$2000,"<"&EDATE($A6,1),'Expense Log'!$D$5:$D$2000,C$4) -> 0 | D6: =SUMIFS('Expense Log'!$G$5:$G$2000,'Expense Log'!$A$5:$A$2000,">="&$A6,'Expense Log'!$A$5:$A$2000,"<"&EDATE($A6,1),'Expense Log'!$D$5:$D$2000,D$4) -> 0 | E6: =SUMIFS('Expense Log'!$G$5:$G$2000,'Expense Log'!$A$5:$A$2000,">="&$A6,'Expense Log'!$A$5:$A$2000,"<"&EDATE($A6,1),'Expense Log'!$D$5:$D$2000,E$4) -> 0 | F6: =SUMIFS('Expense Log'!$G$5:$G$2000,'Expense Log'!$A$5:$A$2000,">="&$A6,'Expense Log'!$A$5:$A$2000,"<"&EDATE($A6,1),'Expense Log'!$D$5:$D$2000,F$4) -> 0 | G6: =SUMIFS('Expense Log'!$G$5:$G$2000,'Expense Log'!$A$5:$A$2000,">="&$A6,'Expense Log'!$A$5:$A$2000,"<"&EDATE($A6,1),'Expense Log'!$D$5:$D$2000,G$4) -> 0 | H6: =SUMIFS('Expense Log'!$G$5:$G$2000,'Expense Log'!$A$5:$A$2000,">="&$A6,'Expense Log'!$A$5:$A$2000,"<"&EDATE($A6,1),'Expense Log'!$D$5:$D$2000,H$4) -> 0 | I6: =SUMIFS('Expense Log'!$G$5:$G$2000,'Expense Log'!$A$5:$A$2000,">="&$A6,'Expense Log'!$A$5:$A$2000,"<"&EDATE($A6,1),'Expense Log'!$D$5:$D$2000,I$4) -> 0 | J6: =SUMIFS('Expense Log'!$G$5:$G$2000,'Expense Log'!$A$5:$A$2000,">="&$A6,'Expense Log'!$A$5:$A$2000,"<"&EDATE($A6,1),'Expense Log'!$D$5:$D$2000,J$4) -> 0 | K6: =SUM(B6:J6) -> 0 | O6: =IF(N(L6)=0,0,K6/L6) -> 0 | P6: =IF(N(M6)=0,0,K6/M6) -> 0 | Q6: =N(N6)-K6 -> 0
A7: 46357 | B7: =SUMIFS('Expense Log'!$G$5:$G$2000,'Expense Log'!$A$5:$A$2000,">="&$A7,'Expense Log'!$A$5:$A$2000,"<"&EDATE($A7,1),'Expense Log'!$D$5:$D$2000,B$4) -> 0 | C7: =SUMIFS('Expense Log'!$G$5:$G$2000,'Expense Log'!$A$5:$A$2000,">="&$A7,'Expense Log'!$A$5:$A$2000,"<"&EDATE($A7,1),'Expense Log'!$D$5:$D$2000,C$4) -> 0 | D7: =SUMIFS('Expense Log'!$G$5:$G$2000,'Expense Log'!$A$5:$A$2000,">="&$A7,'Expense Log'!$A$5:$A$2000,"<"&EDATE($A7,1),'Expense Log'!$D$5:$D$2000,D$4) -> 0 | E7: =SUMIFS('Expense Log'!$G$5:$G$2000,'Expense Log'!$A$5:$A$2000,">="&$A7,'Expense Log'!$A$5:$A$2000,"<"&EDATE($A7,1),'Expense Log'!$D$5:$D$2000,E$4) -> 0 | F7: =SUMIFS('Expense Log'!$G$5:$G$2000,'Expense Log'!$A$5:$A$2000,">="&$A7,'Expense Log'!$A$5:$A$2000,"<"&EDATE($A7,1),'Expense Log'!$D$5:$D$2000,F$4) -> 0 | G7: =SUMIFS('Expense Log'!$G$5:$G$2000,'Expense Log'!$A$5:$A$2000,">="&$A7,'Expense Log'!$A$5:$A$2000,"<"&EDATE($A7,1),'Expense Log'!$D$5:$D$2000,G$4) -> 0 | H7: =SUMIFS('Expense Log'!$G$5:$G$2000,'Expense Log'!$A$5:$A$2000,">="&$A7,'Expense Log'!$A$5:$A$2000,"<"&EDATE($A7,1),'Expense Log'!$D$5:$D$2000,H$4) -> 0 | I7: =SUMIFS('Expense Log'!$G$5:$G$2000,'Expense Log'!$A$5:$A$2000,">="&$A7,'Expense Log'!$A$5:$A$2000,"<"&EDATE($A7,1),'Expense Log'!$D$5:$D$2000,I$4) -> 0 | J7: =SUMIFS('Expense Log'!$G$5:$G$2000,'Expense Log'!$A$5:$A$2000,">="&$A7,'Expense Log'!$A$5:$A$2000,"<"&EDATE($A7,1),'Expense Log'!$D$5:$D$2000,J$4) -> 0 | K7: =SUM(B7:J7) -> 0 | O7: =IF(N(L7)=0,0,K7/L7) -> 0 | P7: =IF(N(M7)=0,0,K7/M7) -> 0 | Q7: =N(N7)-K7 -> 0
A8: 46388 | B8: =SUMIFS('Expense Log'!$G$5:$G$2000,'Expense Log'!$A$5:$A$2000,">="&$A8,'Expense Log'!$A$5:$A$2000,"<"&EDATE($A8,1),'Expense Log'!$D$5:$D$2000,B$4) -> 0 | C8: =SUMIFS('Expense Log'!$G$5:$G$2000,'Expense Log'!$A$5:$A$2000,">="&$A8,'Expense Log'!$A$5:$A$2000,"<"&EDATE($A8,1),'Expense Log'!$D$5:$D$2000,C$4) -> 0 | D8: =SUMIFS('Expense Log'!$G$5:$G$2000,'Expense Log'!$A$5:$A$2000,">="&$A8,'Expense Log'!$A$5:$A$2000,"<"&EDATE($A8,1),'Expense Log'!$D$5:$D$2000,D$4) -> 0 | E8: =SUMIFS('Expense Log'!$G$5:$G$2000,'Expense Log'!$A$5:$A$2000,">="&$A8,'Expense Log'!$A$5:$A$2000,"<"&EDATE($A8,1),'Expense Log'!$D$5:$D$2000,E$4) -> 0 | F8: =SUMIFS('Expense Log'!$G$5:$G$2000,'Expense Log'!$A$5:$A$2000,">="&$A8,'Expense Log'!$A$5:$A$2000,"<"&EDATE($A8,1),'Expense Log'!$D$5:$D$2000,F$4) -> 0 | G8: =SUMIFS('Expense Log'!$G$5:$G$2000,'Expense Log'!$A$5:$A$2000,">="&$A8,'Expense Log'!$A$5:$A$2000,"<"&EDATE($A8,1),'Expense Log'!$D$5:$D$2000,G$4) -> 0 | H8: =SUMIFS('Expense Log'!$G$5:$G$2000,'Expense Log'!$A$5:$A$2000,">="&$A8,'Expense Log'!$A$5:$A$2000,"<"&EDATE($A8,1),'Expense Log'!$D$5:$D$2000,H$4) -> 0 | I8: =SUMIFS('Expense Log'!$G$5:$G$2000,'Expense Log'!$A$5:$A$2000,">="&$A8,'Expense Log'!$A$5:$A$2000,"<"&EDATE($A8,1),'Expense Log'!$D$5:$D$2000,I$4) -> 0 | J8: =SUMIFS('Expense Log'!$G$5:$G$2000,'Expense Log'!$A$5:$A$2000,">="&$A8,'Expense Log'!$A$5:$A$2000,"<"&EDATE($A8,1),'Expense Log'!$D$5:$D$2000,J$4) -> 0 | K8: =SUM(B8:J8) -> 0 | O8: =IF(N(L8)=0,0,K8/L8) -> 0 | P8: =IF(N(M8)=0,0,K8/M8) -> 0 | Q8: =N(N8)-K8 -> 0
A9: 46419 | B9: =SUMIFS('Expense Log'!$G$5:$G$2000,'Expense Log'!$A$5:$A$2000,">="&$A9,'Expense Log'!$A$5:$A$2000,"<"&EDATE($A9,1),'Expense Log'!$D$5:$D$2000,B$4) -> 0 | C9: =SUMIFS('Expense Log'!$G$5:$G$2000,'Expense Log'!$A$5:$A$2000,">="&$A9,'Expense Log'!$A$5:$A$2000,"<"&EDATE($A9,1),'Expense Log'!$D$5:$D$2000,C$4) -> 0 | D9: =SUMIFS('Expense Log'!$G$5:$G$2000,'Expense Log'!$A$5:$A$2000,">="&$A9,'Expense Log'!$A$5:$A$2000,"<"&EDATE($A9,1),'Expense Log'!$D$5:$D$2000,D$4) -> 0 | E9: =SUMIFS('Expense Log'!$G$5:$G$2000,'Expense Log'!$A$5:$A$2000,">="&$A9,'Expense Log'!$A$5:$A$2000,"<"&EDATE($A9,1),'Expense Log'!$D$5:$D$2000,E$4) -> 0 | F9: =SUMIFS('Expense Log'!$G$5:$G$2000,'Expense Log'!$A$5:$A$2000,">="&$A9,'Expense Log'!$A$5:$A$2000,"<"&EDATE($A9,1),'Expense Log'!$D$5:$D$2000,F$4) -> 0 | G9: =SUMIFS('Expense Log'!$G$5:$G$2000,'Expense Log'!$A$5:$A$2000,">="&$A9,'Expense Log'!$A$5:$A$2000,"<"&EDATE($A9,1),'Expense Log'!$D$5:$D$2000,G$4) -> 0 | H9: =SUMIFS('Expense Log'!$G$5:$G$2000,'Expense Log'!$A$5:$A$2000,">="&$A9,'Expense Log'!$A$5:$A$2000,"<"&EDATE($A9,1),'Expense Log'!$D$5:$D$2000,H$4) -> 0 | I9: =SUMIFS('Expense Log'!$G$5:$G$2000,'Expense Log'!$A$5:$A$2000,">="&$A9,'Expense Log'!$A$5:$A$2000,"<"&EDATE($A9,1),'Expense Log'!$D$5:$D$2000,I$4) -> 0 | J9: =SUMIFS('Expense Log'!$G$5:$G$2000,'Expense Log'!$A$5:$A$2000,">="&$A9,'Expense Log'!$A$5:$A$2000,"<"&EDATE($A9,1),'Expense Log'!$D$5:$D$2000,J$4) -> 0 | K9: =SUM(B9:J9) -> 0 | O9: =IF(N(L9)=0,0,K9/L9) -> 0 | P9: =IF(N(M9)=0,0,K9/M9) -> 0 | Q9: =N(N9)-K9 -> 0
A10: 46447 | B10: =SUMIFS('Expense Log'!$G$5:$G$2000,'Expense Log'!$A$5:$A$2000,">="&$A10,'Expense Log'!$A$5:$A$2000,"<"&EDATE($A10,1),'Expense Log'!$D$5:$D$2000,B$4) -> 0 | C10: =SUMIFS('Expense Log'!$G$5:$G$2000,'Expense Log'!$A$5:$A$2000,">="&$A10,'Expense Log'!$A$5:$A$2000,"<"&EDATE($A10,1),'Expense Log'!$D$5:$D$2000,C$4) -> 0 | D10: =SUMIFS('Expense Log'!$G$5:$G$2000,'Expense Log'!$A$5:$A$2000,">="&$A10,'Expense Log'!$A$5:$A$2000,"<"&EDATE($A10,1),'Expense Log'!$D$5:$D$2000,D$4) -> 0 | E10: =SUMIFS('Expense Log'!$G$5:$G$2000,'Expense Log'!$A$5:$A$2000,">="&$A10,'Expense Log'!$A$5:$A$2000,"<"&EDATE($A10,1),'Expense Log'!$D$5:$D$2000,E$4) -> 0 | F10: =SUMIFS('Expense Log'!$G$5:$G$2000,'Expense Log'!$A$5:$A$2000,">="&$A10,'Expense Log'!$A$5:$A$2000,"<"&EDATE($A10,1),'Expense Log'!$D$5:$D$2000,F$4) -> 0 | G10: =SUMIFS('Expense Log'!$G$5:$G$2000,'Expense Log'!$A$5:$A$2000,">="&$A10,'Expense Log'!$A$5:$A$2000,"<"&EDATE($A10,1),'Expense Log'!$D$5:$D$2000,G$4) -> 0 | H10: =SUMIFS('Expense Log'!$G$5:$G$2000,'Expense Log'!$A$5:$A$2000,">="&$A10,'Expense Log'!$A$5:$A$2000,"<"&EDATE($A10,1),'Expense Log'!$D$5:$D$2000,H$4) -> 0 | I10: =SUMIFS('Expense Log'!$G$5:$G$2000,'Expense Log'!$A$5:$A$2000,">="&$A10,'Expense Log'!$A$5:$A$2000,"<"&EDATE($A10,1),'Expense Log'!$D$5:$D$2000,I$4) -> 0 | J10: =SUMIFS('Expense Log'!$G$5:$G$2000,'Expense Log'!$A$5:$A$2000,">="&$A10,'Expense Log'!$A$5:$A$2000,"<"&EDATE($A10,1),'Expense Log'!$D$5:$D$2000,J$4) -> 0 | K10: =SUM(B10:J10) -> 0 | O10: =IF(N(L10)=0,0,K10/L10) -> 0 | P10: =IF(N(M10)=0,0,K10/M10) -> 0 | Q10: =N(N10)-K10 -> 0
A11: 46478 | B11: =SUMIFS('Expense Log'!$G$5:$G$2000,'Expense Log'!$A$5:$A$2000,">="&$A11,'Expense Log'!$A$5:$A$2000,"<"&EDATE($A11,1),'Expense Log'!$D$5:$D$2000,B$4) -> 0 | C11: =SUMIFS('Expense Log'!$G$5:$G$2000,'Expense Log'!$A$5:$A$2000,">="&$A11,'Expense Log'!$A$5:$A$2000,"<"&EDATE($A11,1),'Expense Log'!$D$5:$D$2000,C$4) -> 0 | D11: =SUMIFS('Expense Log'!$G$5:$G$2000,'Expense Log'!$A$5:$A$2000,">="&$A11,'Expense Log'!$A$5:$A$2000,"<"&EDATE($A11,1),'Expense Log'!$D$5:$D$2000,D$4) -> 0 | E11: =SUMIFS('Expense Log'!$G$5:$G$2000,'Expense Log'!$A$5:$A$2000,">="&$A11,'Expense Log'!$A$5:$A$2000,"<"&EDATE($A11,1),'Expense Log'!$D$5:$D$2000,E$4) -> 0 | F11: =SUMIFS('Expense Log'!$G$5:$G$2000,'Expense Log'!$A$5:$A$2000,">="&$A11,'Expense Log'!$A$5:$A$2000,"<"&EDATE($A11,1),'Expense Log'!$D$5:$D$2000,F$4) -> 0 | G11: =SUMIFS('Expense Log'!$G$5:$G$2000,'Expense Log'!$A$5:$A$2000,">="&$A11,'Expense Log'!$A$5:$A$2000,"<"&EDATE($A11,1),'Expense Log'!$D$5:$D$2000,G$4) -> 0 | H11: =SUMIFS('Expense Log'!$G$5:$G$2000,'Expense Log'!$A$5:$A$2000,">="&$A11,'Expense Log'!$A$5:$A$2000,"<"&EDATE($A11,1),'Expense Log'!$D$5:$D$2000,H$4) -> 0 | I11: =SUMIFS('Expense Log'!$G$5:$G$2000,'Expense Log'!$A$5:$A$2000,">="&$A11,'Expense Log'!$A$5:$A$2000,"<"&EDATE($A11,1),'Expense Log'!$D$5:$D$2000,I$4) -> 0 | J11: =SUMIFS('Expense Log'!$G$5:$G$2000,'Expense Log'!$A$5:$A$2000,">="&$A11,'Expense Log'!$A$5:$A$2000,"<"&EDATE($A11,1),'Expense Log'!$D$5:$D$2000,J$4) -> 0 | K11: =SUM(B11:J11) -> 0 | O11: =IF(N(L11)=0,0,K11/L11) -> 0 | P11: =IF(N(M11)=0,0,K11/M11) -> 0 | Q11: =N(N11)-K11 -> 0
A12: 46508 | B12: =SUMIFS('Expense Log'!$G$5:$G$2000,'Expense Log'!$A$5:$A$2000,">="&$A12,'Expense Log'!$A$5:$A$2000,"<"&EDATE($A12,1),'Expense Log'!$D$5:$D$2000,B$4) -> 0 | C12: =SUMIFS('Expense Log'!$G$5:$G$2000,'Expense Log'!$A$5:$A$2000,">="&$A12,'Expense Log'!$A$5:$A$2000,"<"&EDATE($A12,1),'Expense Log'!$D$5:$D$2000,C$4) -> 0 | D12: =SUMIFS('Expense Log'!$G$5:$G$2000,'Expense Log'!$A$5:$A$2000,">="&$A12,'Expense Log'!$A$5:$A$2000,"<"&EDATE($A12,1),'Expense Log'!$D$5:$D$2000,D$4) -> 0 | E12: =SUMIFS('Expense Log'!$G$5:$G$2000,'Expense Log'!$A$5:$A$2000,">="&$A12,'Expense Log'!$A$5:$A$2000,"<"&EDATE($A12,1),'Expense Log'!$D$5:$D$2000,E$4) -> 0 | F12: =SUMIFS('Expense Log'!$G$5:$G$2000,'Expense Log'!$A$5:$A$2000,">="&$A12,'Expense Log'!$A$5:$A$2000,"<"&EDATE($A12,1),'Expense Log'!$D$5:$D$2000,F$4) -> 0 | G12: =SUMIFS('Expense Log'!$G$5:$G$2000,'Expense Log'!$A$5:$A$2000,">="&$A12,'Expense Log'!$A$5:$A$2000,"<"&EDATE($A12,1),'Expense Log'!$D$5:$D$2000,G$4) -> 0 | H12: =SUMIFS('Expense Log'!$G$5:$G$2000,'Expense Log'!$A$5:$A$2000,">="&$A12,'Expense Log'!$A$5:$A$2000,"<"&EDATE($A12,1),'Expense Log'!$D$5:$D$2000,H$4) -> 0 | I12: =SUMIFS('Expense Log'!$G$5:$G$2000,'Expense Log'!$A$5:$A$2000,">="&$A12,'Expense Log'!$A$5:$A$2000,"<"&EDATE($A12,1),'Expense Log'!$D$5:$D$2000,I$4) -> 0 | J12: =SUMIFS('Expense Log'!$G$5:$G$2000,'Expense Log'!$A$5:$A$2000,">="&$A12,'Expense Log'!$A$5:$A$2000,"<"&EDATE($A12,1),'Expense Log'!$D$5:$D$2000,J$4) -> 0 | K12: =SUM(B12:J12) -> 0 | O12: =IF(N(L12)=0,0,K12/L12) -> 0 | P12: =IF(N(M12)=0,0,K12/M12) -> 0 | Q12: =N(N12)-K12 -> 0
A13: 46539 | B13: =SUMIFS('Expense Log'!$G$5:$G$2000,'Expense Log'!$A$5:$A$2000,">="&$A13,'Expense Log'!$A$5:$A$2000,"<"&EDATE($A13,1),'Expense Log'!$D$5:$D$2000,B$4) -> 0 | C13: =SUMIFS('Expense Log'!$G$5:$G$2000,'Expense Log'!$A$5:$A$2000,">="&$A13,'Expense Log'!$A$5:$A$2000,"<"&EDATE($A13,1),'Expense Log'!$D$5:$D$2000,C$4) -> 0 | D13: =SUMIFS('Expense Log'!$G$5:$G$2000,'Expense Log'!$A$5:$A$2000,">="&$A13,'Expense Log'!$A$5:$A$2000,"<"&EDATE($A13,1),'Expense Log'!$D$5:$D$2000,D$4) -> 0 | E13: =SUMIFS('Expense Log'!$G$5:$G$2000,'Expense Log'!$A$5:$A$2000,">="&$A13,'Expense Log'!$A$5:$A$2000,"<"&EDATE($A13,1),'Expense Log'!$D$5:$D$2000,E$4) -> 0 | F13: =SUMIFS('Expense Log'!$G$5:$G$2000,'Expense Log'!$A$5:$A$2000,">="&$A13,'Expense Log'!$A$5:$A$2000,"<"&EDATE($A13,1),'Expense Log'!$D$5:$D$2000,F$4) -> 0 | G13: =SUMIFS('Expense Log'!$G$5:$G$2000,'Expense Log'!$A$5:$A$2000,">="&$A13,'Expense Log'!$A$5:$A$2000,"<"&EDATE($A13,1),'Expense Log'!$D$5:$D$2000,G$4) -> 0 | H13: =SUMIFS('Expense Log'!$G$5:$G$2000,'Expense Log'!$A$5:$A$2000,">="&$A13,'Expense Log'!$A$5:$A$2000,"<"&EDATE($A13,1),'Expense Log'!$D$5:$D$2000,H$4) -> 0 | I13: =SUMIFS('Expense Log'!$G$5:$G$2000,'Expense Log'!$A$5:$A$2000,">="&$A13,'Expense Log'!$A$5:$A$2000,"<"&EDATE($A13,1),'Expense Log'!$D$5:$D$2000,I$4) -> 0 | J13: =SUMIFS('Expense Log'!$G$5:$G$2000,'Expense Log'!$A$5:$A$2000,">="&$A13,'Expense Log'!$A$5:$A$2000,"<"&EDATE($A13,1),'Expense Log'!$D$5:$D$2000,J$4) -> 0 | K13: =SUM(B13:J13) -> 0 | O13: =IF(N(L13)=0,0,K13/L13) -> 0 | P13: =IF(N(M13)=0,0,K13/M13) -> 0 | Q13: =N(N13)-K13 -> 0
A14: 46569 | B14: =SUMIFS('Expense Log'!$G$5:$G$2000,'Expense Log'!$A$5:$A$2000,">="&$A14,'Expense Log'!$A$5:$A$2000,"<"&EDATE($A14,1),'Expense Log'!$D$5:$D$2000,B$4) -> 0 | C14: =SUMIFS('Expense Log'!$G$5:$G$2000,'Expense Log'!$A$5:$A$2000,">="&$A14,'Expense Log'!$A$5:$A$2000,"<"&EDATE($A14,1),'Expense Log'!$D$5:$D$2000,C$4) -> 0 | D14: =SUMIFS('Expense Log'!$G$5:$G$2000,'Expense Log'!$A$5:$A$2000,">="&$A14,'Expense Log'!$A$5:$A$2000,"<"&EDATE($A14,1),'Expense Log'!$D$5:$D$2000,D$4) -> 0 | E14: =SUMIFS('Expense Log'!$G$5:$G$2000,'Expense Log'!$A$5:$A$2000,">="&$A14,'Expense Log'!$A$5:$A$2000,"<"&EDATE($A14,1),'Expense Log'!$D$5:$D$2000,E$4) -> 0 | F14: =SUMIFS('Expense Log'!$G$5:$G$2000,'Expense Log'!$A$5:$A$2000,">="&$A14,'Expense Log'!$A$5:$A$2000,"<"&EDATE($A14,1),'Expense Log'!$D$5:$D$2000,F$4) -> 0 | G14: =SUMIFS('Expense Log'!$G$5:$G$2000,'Expense Log'!$A$5:$A$2000,">="&$A14,'Expense Log'!$A$5:$A$2000,"<"&EDATE($A14,1),'Expense Log'!$D$5:$D$2000,G$4) -> 0 | H14: =SUMIFS('Expense Log'!$G$5:$G$2000,'Expense Log'!$A$5:$A$2000,">="&$A14,'Expense Log'!$A$5:$A$2000,"<"&EDATE($A14,1),'Expense Log'!$D$5:$D$2000,H$4) -> 0 | I14: =SUMIFS('Expense Log'!$G$5:$G$2000,'Expense Log'!$A$5:$A$2000,">="&$A14,'Expense Log'!$A$5:$A$2000,"<"&EDATE($A14,1),'Expense Log'!$D$5:$D$2000,I$4) -> 0 | J14: =SUMIFS('Expense Log'!$G$5:$G$2000,'Expense Log'!$A$5:$A$2000,">="&$A14,'Expense Log'!$A$5:$A$2000,"<"&EDATE($A14,1),'Expense Log'!$D$5:$D$2000,J$4) -> 0 | K14: =SUM(B14:J14) -> 0 | O14: =IF(N(L14)=0,0,K14/L14) -> 0 | P14: =IF(N(M14)=0,0,K14/M14) -> 0 | Q14: =N(N14)-K14 -> 0
A15: 46600 | B15: =SUMIFS('Expense Log'!$G$5:$G$2000,'Expense Log'!$A$5:$A$2000,">="&$A15,'Expense Log'!$A$5:$A$2000,"<"&EDATE($A15,1),'Expense Log'!$D$5:$D$2000,B$4) -> 0 | C15: =SUMIFS('Expense Log'!$G$5:$G$2000,'Expense Log'!$A$5:$A$2000,">="&$A15,'Expense Log'!$A$5:$A$2000,"<"&EDATE($A15,1),'Expense Log'!$D$5:$D$2000,C$4) -> 0 | D15: =SUMIFS('Expense Log'!$G$5:$G$2000,'Expense Log'!$A$5:$A$2000,">="&$A15,'Expense Log'!$A$5:$A$2000,"<"&EDATE($A15,1),'Expense Log'!$D$5:$D$2000,D$4) -> 0 | E15: =SUMIFS('Expense Log'!$G$5:$G$2000,'Expense Log'!$A$5:$A$2000,">="&$A15,'Expense Log'!$A$5:$A$2000,"<"&EDATE($A15,1),'Expense Log'!$D$5:$D$2000,E$4) -> 0 | F15: =SUMIFS('Expense Log'!$G$5:$G$2000,'Expense Log'!$A$5:$A$2000,">="&$A15,'Expense Log'!$A$5:$A$2000,"<"&EDATE($A15,1),'Expense Log'!$D$5:$D$2000,F$4) -> 0 | G15: =SUMIFS('Expense Log'!$G$5:$G$2000,'Expense Log'!$A$5:$A$2000,">="&$A15,'Expense Log'!$A$5:$A$2000,"<"&EDATE($A15,1),'Expense Log'!$D$5:$D$2000,G$4) -> 0 | H15: =SUMIFS('Expense Log'!$G$5:$G$2000,'Expense Log'!$A$5:$A$2000,">="&$A15,'Expense Log'!$A$5:$A$2000,"<"&EDATE($A15,1),'Expense Log'!$D$5:$D$2000,H$4) -> 0 | I15: =SUMIFS('Expense Log'!$G$5:$G$2000,'Expense Log'!$A$5:$A$2000,">="&$A15,'Expense Log'!$A$5:$A$2000,"<"&EDATE($A15,1),'Expense Log'!$D$5:$D$2000,I$4) -> 0 | J15: =SUMIFS('Expense Log'!$G$5:$G$2000,'Expense Log'!$A$5:$A$2000,">="&$A15,'Expense Log'!$A$5:$A$2000,"<"&EDATE($A15,1),'Expense Log'!$D$5:$D$2000,J$4) -> 0 | K15: =SUM(B15:J15) -> 0 | O15: =IF(N(L15)=0,0,K15/L15) -> 0 | P15: =IF(N(M15)=0,0,K15/M15) -> 0 | Q15: =N(N15)-K15 -> 0
A16: 46631 | B16: =SUMIFS('Expense Log'!$G$5:$G$2000,'Expense Log'!$A$5:$A$2000,">="&$A16,'Expense Log'!$A$5:$A$2000,"<"&EDATE($A16,1),'Expense Log'!$D$5:$D$2000,B$4) -> 0 | C16: =SUMIFS('Expense Log'!$G$5:$G$2000,'Expense Log'!$A$5:$A$2000,">="&$A16,'Expense Log'!$A$5:$A$2000,"<"&EDATE($A16,1),'Expense Log'!$D$5:$D$2000,C$4) -> 0 | D16: =SUMIFS('Expense Log'!$G$5:$G$2000,'Expense Log'!$A$5:$A$2000,">="&$A16,'Expense Log'!$A$5:$A$2000,"<"&EDATE($A16,1),'Expense Log'!$D$5:$D$2000,D$4) -> 0 | E16: =SUMIFS('Expense Log'!$G$5:$G$2000,'Expense Log'!$A$5:$A$2000,">="&$A16,'Expense Log'!$A$5:$A$2000,"<"&EDATE($A16,1),'Expense Log'!$D$5:$D$2000,E$4) -> 0 | F16: =SUMIFS('Expense Log'!$G$5:$G$2000,'Expense Log'!$A$5:$A$2000,">="&$A16,'Expense Log'!$A$5:$A$2000,"<"&EDATE($A16,1),'Expense Log'!$D$5:$D$2000,F$4) -> 0 | G16: =SUMIFS('Expense Log'!$G$5:$G$2000,'Expense Log'!$A$5:$A$2000,">="&$A16,'Expense Log'!$A$5:$A$2000,"<"&EDATE($A16,1),'Expense Log'!$D$5:$D$2000,G$4) -> 0 | H16: =SUMIFS('Expense Log'!$G$5:$G$2000,'Expense Log'!$A$5:$A$2000,">="&$A16,'Expense Log'!$A$5:$A$2000,"<"&EDATE($A16,1),'Expense Log'!$D$5:$D$2000,H$4) -> 0 | I16: =SUMIFS('Expense Log'!$G$5:$G$2000,'Expense Log'!$A$5:$A$2000,">="&$A16,'Expense Log'!$A$5:$A$2000,"<"&EDATE($A16,1),'Expense Log'!$D$5:$D$2000,I$4) -> 0 | J16: =SUMIFS('Expense Log'!$G$5:$G$2000,'Expense Log'!$A$5:$A$2000,">="&$A16,'Expense Log'!$A$5:$A$2000,"<"&EDATE($A16,1),'Expense Log'!$D$5:$D$2000,J$4) -> 0 | K16: =SUM(B16:J16) -> 0 | O16: =IF(N(L16)=0,0,K16/L16) -> 0 | P16: =IF(N(M16)=0,0,K16/M16) -> 0 | Q16: =N(N16)-K16 -> 0
A17: 12-month total | B17: =SUM(B5:B16) -> 7 | C17: =SUM(C5:C16) -> 0 | D17: =SUM(D5:D16) -> 0 | E17: =SUM(E5:E16) -> 0 | F17: =SUM(F5:F16) -> 0 | G17: =SUM(G5:G16) -> 0 | H17: =SUM(H5:H16) -> 0 | I17: =SUM(I5:I16) -> 0 | ... K17: =SUM(K5:K16) -> 7 | N17: =SUM(N5:N16) -> 0 | Q17: =SUM(Q5:Q16) -> -7
A19: Need more months? Copy row 16 down and change the date; the formulas carry over. Uncategorized log rows are not counted - pick a category for every expense.
